tgscraper/__init__.py
tgscraper/tgs_config.toml.example
tgscraper/tgscraper.py
tgscraper-0.1.3.dist-info/WHEEL
tgscraper-0.1.3.dist-info/METADATA
tgscraper-0.1.3.dist-info/RECORD
