Metadata-Version: 2.1
Name: tgscraper
Version: 0.1.3
Summary: Demo version of a package for easy telegram scraping
Home-page: https://github.com/timofeiryko/tgscraper
License: MIT
Author: Timofei Ryko
Author-email: timofei.ryko@gmail.com
Requires-Python: >=3.11,<4.0
Classifier: License :: OSI Approved :: MIT License
Classifier: Programming Language :: Python :: 3
Classifier: Programming Language :: Python :: 3.11
Requires-Dist: pandas (>=1.5.2,<2.0.0)
Requires-Dist: pydantic (>=1.10.4,<2.0.0)
Requires-Dist: telethon (>=1.26.1,<2.0.0)
